stacie/__init__.py
stacie/conditioning.py
stacie/cost.py
stacie/cutoff.py
stacie/estimate.py
stacie/model.py
stacie/plot.py
stacie/spectrum.py
stacie/synthetic.py
stacie/utils.py
stacie-1.2.1.dist-info/licenses/LICENSE-CC-BY-SA-4.0.txt
stacie-1.2.1.dist-info/licenses/LICENSE-LGPL-3.0-or-later.txt
stacie-1.2.1.dist-info/METADATA
stacie-1.2.1.dist-info/WHEEL
stacie-1.2.1.dist-info/top_level.txt
stacie-1.2.1.dist-info/RECORD
