Metadata-Version: 2.4
Name: stacie
Version: 1.2.1
Summary: STable AutoCorrelation Integral Estimator (STACIE)
Author-email: Gözdenur Toraman <gozdenur.toraman@ugent.be>, Toon Verstraelen <toon.verstraelen@ugent.be>
License-Expression: LGPL-3.0-or-later
Project-URL: Documentation, https://molmod.github.io/stacie/
Project-URL: Issues, https://github.com/molmod/stacie/issues/
Project-URL: Source, https://github.com/molmod/stacie/
Classifier: Development Status :: 5 - Production/Stable
Classifier: Environment :: Console
Classifier: Intended Audience :: Education
Classifier: Intended Audience :: Science/Research
Classifier: Operating System :: POSIX :: Linux
Classifier: Operating System :: MacOS
Classifier: Operating System :: Microsoft :: Windows
Classifier: Programming Language :: Python :: 3
Classifier: Programming Language :: Python :: 3 :: Only
Classifier: Programming Language :: Python :: 3.10
Classifier: Programming Language :: Python :: 3.11
Classifier: Programming Language :: Python :: 3.12
Classifier: Programming Language :: Python :: 3.13
Classifier: Programming Language :: Python :: 3.14
Requires-Python: >=3.10
License-File: LICENSE-CC-BY-SA-4.0.txt
License-File: LICENSE-LGPL-3.0-or-later.txt
Requires-Dist: attrs>=23.1.0
Requires-Dist: matplotlib>=3.9.0
Requires-Dist: numpy>=2.0.0
Requires-Dist: scipy>=1.13.0
Requires-Dist: typing-extensions>=4.8.0; python_version < "3.11"
Provides-Extra: docs
Requires-Dist: furo; extra == "docs"
Requires-Dist: intersphinx-registry; extra == "docs"
Requires-Dist: jupyter; extra == "docs"
Requires-Dist: jupyter-cache; extra == "docs"
Requires-Dist: jupytext; extra == "docs"
Requires-Dist: mdtraj; extra == "docs"
Requires-Dist: myst-nb; extra == "docs"
Requires-Dist: myst-parser; extra == "docs"
Requires-Dist: nglview; extra == "docs"
Requires-Dist: numpydoc; extra == "docs"
Requires-Dist: openmm>=8.0; extra == "docs"
Requires-Dist: packaging; extra == "docs"
Requires-Dist: pandas; extra == "docs"
Requires-Dist: setuptools_scm; extra == "docs"
Requires-Dist: sphinx; extra == "docs"
Requires-Dist: sphinx-autobuild; extra == "docs"
Requires-Dist: sphinx-autodoc-typehints; extra == "docs"
Requires-Dist: sphinx-codeautolink; extra == "docs"
Requires-Dist: sphinx-copybutton; extra == "docs"
Requires-Dist: sphinx-tippy; extra == "docs"
Requires-Dist: sphinxcontrib-bibtex; extra == "docs"
Requires-Dist: sphinxcontrib-svg2pdfconverter; extra == "docs"
Requires-Dist: stepup>=3.1.2; extra == "docs"
Requires-Dist: stepup-reprep>=3.1.5; extra == "docs"
Provides-Extra: tests
Requires-Dist: pytest; extra == "tests"
Requires-Dist: pytest-regtest; extra == "tests"
Requires-Dist: pytest-xdist; extra == "tests"
Requires-Dist: numdifftools; extra == "tests"
Dynamic: license-file
